engibench/__init__.py
engibench/constraint.py
engibench/core.py
engibench/problems/__init__.py
engibench/problems/airfoil/__init__.py
engibench/problems/airfoil/pyopt_history.py
engibench/problems/airfoil/utils.py
engibench/problems/airfoil/v0.py
engibench/problems/airfoil/templates/airfoil_analysis.py
engibench/problems/airfoil/templates/airfoil_opt.py
engibench/problems/airfoil/templates/pre_process.py
engibench/problems/beams2d/__init__.py
engibench/problems/beams2d/backend.py
engibench/problems/beams2d/v0.py
engibench/problems/heatconduction2d/__init__.py
engibench/problems/heatconduction2d/v0.py
engibench/problems/heatconduction2d/templates/initialize_design_2d.py
engibench/problems/heatconduction2d/templates/optimize_heat_conduction_2d.py
engibench/problems/heatconduction2d/templates/simulate_heat_conduction_2d.py
engibench/problems/heatconduction3d/__init__.py
engibench/problems/heatconduction3d/v0.py
engibench/problems/heatconduction3d/templates/initialize_design_3d.py
engibench/problems/heatconduction3d/templates/optimize_heat_conduction_3d.py
engibench/problems/heatconduction3d/templates/simulate_heat_conduction_3d.py
engibench/problems/photonics2d/__init__.py
engibench/problems/photonics2d/backend.py
engibench/problems/photonics2d/dataset_slurm_test.py
engibench/problems/photonics2d/v0.py
engibench/problems/power_electronics/__init__.py
engibench/problems/power_electronics/v0.py
engibench/problems/power_electronics/data/5_4_3_6_10-dcdc_converter_1.net
engibench/problems/power_electronics/utils/__init__.py
engibench/problems/power_electronics/utils/config.py
engibench/problems/power_electronics/utils/constants.py
engibench/problems/power_electronics/utils/netlist_handler.py
engibench/problems/power_electronics/utils/ngspice.py
engibench/problems/power_electronics/utils/process_log_file.py
engibench/problems/power_electronics/utils/process_sweep_data.py
engibench/problems/thermoelastic2d/__init__.py
engibench/problems/thermoelastic2d/utils.py
engibench-0.0.1.dist-info/licenses/LICENSE
engibench-0.0.1.dist-info/METADATA
engibench-0.0.1.dist-info/WHEEL
engibench-0.0.1.dist-info/top_level.txt
engibench-0.0.1.dist-info/RECORD
