Metadata-Version: 2.4
Name: engibench
Version: 0.0.1
Summary: A suite of benchmarks for automated engineering design.
Author-email: Florian Felten <ffelten@mavt.ethz.ch>
License: GPL-3.0
Project-URL: Homepage, https://ideal.ethz.ch/
Project-URL: Repository, https://github.com/IDEALLab/EngiBench
Project-URL: Documentation, https://engibench.ethz.ch
Project-URL: Bug Report, https://github.com/IDEALLab/EngiBench/issues
Keywords: Mechanical Engineering,Machine Learning,AI,Optimization
Classifier: Development Status :: 4 - Beta
Classifier: Programming Language :: Python :: 3
Classifier: Programming Language :: Python :: 3.10
Classifier: Programming Language :: Python :: 3.11
Classifier: Programming Language :: Python :: 3.12
Classifier: Intended Audience :: Science/Research
Classifier: Topic :: Scientific/Engineering :: Artificial Intelligence
Requires-Python: >=3.10
License-File: LICENSE
Requires-Dist: numpy<=2.0
Requires-Dist: gymnasium>=1.0.0
Requires-Dist: datasets[vision]>=3.1.0
Requires-Dist: pandas>=2.2.3
Requires-Dist: matplotlib>=3.9.3
Requires-Dist: pyarrow<20.0.0,>=15.0.0
Provides-Extra: airfoil
Requires-Dist: sqlitedict>=1.6; extra == "airfoil"
Provides-Extra: electronics
Requires-Dist: networkx>=3.2.1; extra == "electronics"
Provides-Extra: beams2d
Requires-Dist: cvxopt>=1.3.2; extra == "beams2d"
Requires-Dist: seaborn; extra == "beams2d"
Provides-Extra: thermoelastic2d
Requires-Dist: cvxopt>=1.3.2; extra == "thermoelastic2d"
Requires-Dist: mmapy>=0.3.0; extra == "thermoelastic2d"
Provides-Extra: photonics2d
Requires-Dist: ceviche>=0.1.3; extra == "photonics2d"
Provides-Extra: all
Requires-Dist: engibench[airfoil,beams2d,electronics,photonics2d,thermoelastic2d]; extra == "all"
Provides-Extra: doc
Requires-Dist: sphinx; extra == "doc"
Requires-Dist: sphinx-autobuild; extra == "doc"
Requires-Dist: myst-parser; extra == "doc"
Requires-Dist: sphinx-gallery==0.14.0; extra == "doc"
Requires-Dist: sphinx-book-theme; extra == "doc"
Requires-Dist: sphinx_github_changelog; extra == "doc"
Requires-Dist: tabulate; extra == "doc"
Provides-Extra: testing
Requires-Dist: pytest>=8.3.2; extra == "testing"
Provides-Extra: dev
Requires-Dist: engibench[all,doc,testing]; extra == "dev"
Dynamic: license-file
